{
    "system" : {
        "log" : "server.log"
    },
    "crypto" : {
        "mpk_file" : "mpk.conf",
        "mpk_len_file" : "mpk-len.conf"
    },
    "id" : {
        "id" : "Client", 
        "ip_address" : "127.0.0.1",
        "port" : 16001,
        "parent" : {
            "id" : "Server", 
            "ip_address" : "127.0.0.1",
            "port" : 5003,
            "parent" : null            
        }
    },
    "init": {
        "user_ids": [
            {
                "id" : "Server", 
                "ip_address" : "127.0.0.1",
                "port" : 5003,
                "parent" : null
            },
            {
                "id" : "Client", 
                "ip_address" : "127.0.0.1",
                "port" : 16001,
                "parent" : {
                    "id" : "Server", 
                    "ip_address" : "127.0.0.1",
                    "port" : 5003,
                    "parent" : null            
                }
            }
        ]
    }

}
